{
	"configurations" : 
	[
		{
			"directories" : 
			[
				{
					"build" : ".",
					"jsonFile" : "directory-.-Debug-f5ebdc15457944623624.json",
					"minimumCMakeVersion" : 
					{
						"string" : "3.21"
					},
					"projectIndex" : 0,
					"source" : ".",
					"targetIndexes" : 
					[
						0
					]
				}
			],
			"name" : "Debug",
			"projects" : 
			[
				{
					"directoryIndexes" : 
					[
						0
					],
					"name" : "Ejercicio3_1Libro",
					"targetIndexes" : 
					[
						0
					]
				}
			],
			"targets" : 
			[
				{
					"directoryIndex" : 0,
					"id" : "Ejercicio3_1Libro::@6890427a1f51a3e7e1df",
					"jsonFile" : "target-Ejercicio3_1Libro-Debug-13d085f8d65696e2b619.json",
					"name" : "Ejercicio3_1Libro",
					"projectIndex" : 0
				}
			]
		}
	],
	"kind" : "codemodel",
	"paths" : 
	{
		"build" : "/media/zerokullneo/Datos/Proyectos/POO/Ejercicio3.1Libro/cmake-build-debug",
		"source" : "/media/zerokullneo/Datos/Proyectos/POO/Ejercicio3.1Libro"
	},
	"version" : 
	{
		"major" : 2,
		"minor" : 3
	}
}
